<?xml version="1.0" encoding="utf-8"?>
<search>
  
  
  
  <entry>
    <title>博客计划</title>
    <link href="/2025/05/31/plan/"/>
    <url>/2025/05/31/plan/</url>
    
    <content type="html"><![CDATA[<p>[TOC]</p><h2 id="1-前言"><a href="#1-前言" class="headerlink" title="1. 前言"></a>1. 前言</h2><p><strong>“凡事预则立，不预则废。”</strong><br>这句话强调了事前规划和准备的重要性，只有提前做好打算，事情才能顺利进行。对于长期的目标和计划，要有清晰的方向和宏观的视野，才能让事情按照预期发展。</p><hr><h2 id="2-顶层设计"><a href="#2-顶层设计" class="headerlink" title="2. 顶层设计"></a>2. 顶层设计</h2><h3 id="2-1-前期准备"><a href="#2-1-前期准备" class="headerlink" title="2.1 前期准备"></a>2.1 前期准备</h3><p><strong>“工欲善其事，必先利其器。”</strong><br>这句话强调了工具对工作的重要性。在进行博客创作时，选择合适的工具和平台，可以提高工作效率和质量。</p><ul><li>Markdown 是一种轻量级的标记语言，适用于编写格式化文本。它的语法简单易学，能够快速生成 HTML 文档，非常适合博客和文档编写。</li><li>VS Code 是一款强大的代码编辑器，支持多种编程语言和插件，可以帮助我们更高效地编写和管理 Markdown 文档。</li><li>Hexo 是一个基于 Markdown 的静态网站生成器，能够将 Markdown 文件转换为静态网页。它支持多种主题和插件，可以帮助我们快速搭建博客网站。</li></ul><p>因此，选择 Markdown、VS Code 和 Hexo 作为博客创作工具和平台，可以显著提升效率和质量。</p><p><strong>“器为辅，技为本。”</strong><br>工具重要，但更关键的是自身的能力和表达技巧。作为芯片设计爱好者，我专注于数字电路设计、代码编写和 FPGA 开发。善用汉语和英语，有助于更好地表达和传播知识。</p><p>前期准备为后续发展打下坚实基础，接下来需要明确长期目标和发展方向。</p><h3 id="2-2-长期目标"><a href="#2-2-长期目标" class="headerlink" title="2.2 长期目标"></a>2.2 长期目标</h3><p><strong>“先后有序，循序渐进。”</strong><br>VS Code、Markdown 和 Hexo 是博客创作的基础工具，需优先掌握。</p><p><strong>“千里之行，始于足下。”</strong><br>工具是用来提高工作效率的，博客质量取决于知识积累和表达能力，因此需持续学习和提升。</p><p><strong>“无规矩不成方圆。”</strong><br>“一流企业做标准、二流企业做品牌、三流企业做产品。”伟大的东西是有体系的、有标准的、有规范的。在代码编写和文档创作中，遵循一定的规范和标准，可以提高代码和文档的可读性和可维护性。制定一套适合自己的 Markdown 规范和 Code Style，是体现个人风格和专业水平的重要方式。</p><p><strong>“书籍是人类进步的阶梯。”</strong><br>书籍是知识的载体，阅读是获取知识和开拓视野的重要途经。“好记性不如烂笔头。”记笔记是帮助我们更好地理解和吸收知识的有效方式。</p><p><strong>“纸上得来终觉浅，绝知此事要躬行。”</strong><br>阅读只是了解，真正的知识是能为自身所用的。只有通过实践，才能真正掌握和理解知识。“实践是检验真理的唯一标准。”、“实践出真知。”说的都是这个道理。故在专业学习中要有实操，如编写代码、跑仿真等；在文档创作中要有实践，如编写博客、撰写论文等。</p><p>为了更好地组织内容和便于读者查阅，对博客内容进行如下专栏划分：</p><h3 id="2-3-专栏划分"><a href="#2-3-专栏划分" class="headerlink" title="2.3 专栏划分"></a>2.3 专栏划分</h3><ul><li>技术篇</li><li>生活篇</li><li>感悟篇</li><li>个人主页</li></ul><!-- TODO: 这里需要完善 --><p>有了清晰的规划和内容结构，接下来需要制定具体的实施措施。</p><hr><h2 id="3-具体措施"><a href="#3-具体措施" class="headerlink" title="3. 具体措施"></a>3. 具体措施</h2><h3 id="3-1-VS-Code-学习"><a href="#3-1-VS-Code-学习" class="headerlink" title="3.1 VS Code 学习"></a>3.1 VS Code 学习</h3><p>在学习和使用 VS Code 的过程中，可以通过以下方式提高自己的使用效率：</p><h4 id="3-1-1-使用插件"><a href="#3-1-1-使用插件" class="headerlink" title="3.1.1 使用插件"></a>3.1.1 使用插件</h4><p>VS Code 拥有强大的插件生态，可以根据自己的需求安装各种插件来增强编辑器的功能和体验。</p><table><thead><tr><th>插件名称</th><th>功能描述</th></tr></thead><tbody><tr><td>GitHub Copilot</td><td>AI 工具，提供代码补全和建议</td></tr><tr><td>Markdown All in One</td><td>提供 Markdown 语法高亮、预览等功能</td></tr><tr><td>Live Preview</td><td>实时预览 Markdown 文档</td></tr></tbody></table><!-- TODO: 这里需要完善 --><h4 id="3-1-2-配置工作区"><a href="#3-1-2-配置工作区" class="headerlink" title="3.1.2. 配置工作区"></a>3.1.2. 配置工作区</h4><p>合理配置 VS Code 的工作区，可以提高我们的开发效率。可以通过设置文件、任务配置等方式，来定制自己的开发环境。</p><h4 id="3-1-3-掌握快捷键"><a href="#3-1-3-掌握快捷键" class="headerlink" title="3.1.3. 掌握快捷键"></a>3.1.3. 掌握快捷键</h4><p>VS Code 提供了丰富的快捷键，可以大大提高我们的编码效率。可以通过学习和记忆常用的快捷键，来减少对鼠标的依赖，提高工作效率。</p><table><thead><tr><th>快捷键</th><th>功能描述</th></tr></thead><tbody><tr><td><code>Ctrl + P</code></td><td>快速打开文件</td></tr><tr><td><code>Ctrl + Shift + P</code></td><td>打开命令面板</td></tr><tr><td><code>Ctrl + B</code></td><td>切换侧边栏</td></tr><tr><td><code>Ctrl + /</code></td><td>注释&#x2F;取消注释选中行</td></tr></tbody></table><!-- TODO: 这里需要完善 --><h4 id="3-1-4-使用版本控制"><a href="#3-1-4-使用版本控制" class="headerlink" title="3.1.4. 使用版本控制"></a>3.1.4. 使用版本控制</h4><p>VS Code 内置了 Git 支持，可以方便地进行版本控制和协作。可以通过 Git 来管理代码的版本，记录修改历史，方便回溯和协作。</p><p>学习教程有<a href="https://mp.weixin.qq.com/s/Bf7uVhGiu47uOELjmC5uXQ">视频同步笔记：狂神聊Git</a>和<a href="https://www.bilibili.com/video/BV1FE411P7B3/?spm_id_from=333.337.search-card.all.click&vd_source=9bd2e1b1436a7e21f867a824355514d5">【狂神说Java】Git最新教程通俗易懂</a>。</p><h3 id="3-2-markdown-学习"><a href="#3-2-markdown-学习" class="headerlink" title="3.2 markdown 学习"></a>3.2 markdown 学习</h3><h4 id="3-2-1-学习资料"><a href="#3-2-1-学习资料" class="headerlink" title="3.2.1 学习资料"></a>3.2.1 学习资料</h4><p>在线网站有 <a href="https://markdown.com.cn/basic-syntax/">Markdown 基本语法</a>和 <a href="https://markdown.com.cn/extended-syntax/">Markdown 扩展语法</a>，书籍有毕小朋的《了不起的 Markdown》。</p><h4 id="3-2-2-学习笔记"><a href="#3-2-2-学习笔记" class="headerlink" title="3.2.2 学习笔记"></a>3.2.2 学习笔记</h4><!-- TODO: 这里需要完善 --><h3 id="3-3-hexo-学习"><a href="#3-3-hexo-学习" class="headerlink" title="3.3 hexo 学习"></a>3.3 hexo 学习</h3><h4 id="3-3-1-学习资料"><a href="#3-3-1-学习资料" class="headerlink" title="3.3.1 学习资料"></a>3.3.1 学习资料</h4><p>视频教程有<a href="https://www.bilibili.com/video/BV1Yb411a7ty/?spm_id_from=333.337.search-card.all.click&vd_source=9bd2e1b1436a7e21f867a824355514d5">手把手教你从0开始搭建自己的个人博客 |无坑版视频教程| hexo</a>。</p><hr><h2 id="4-总结与展望"><a href="#4-总结与展望" class="headerlink" title="4. 总结与展望"></a>4. 总结与展望</h2><!-- TODO: 这里需要完善 -->]]></content>
    
    
    <categories>
      
      <category>计划</category>
      
    </categories>
    
    
    <tags>
      
      <tag>保密</tag>
      
      <tag>计划</tag>
      
      <tag>全局</tag>
      
    </tags>
    
  </entry>
  
  
  
  <entry>
    <title>Hexo+GitHub/Gitee博客操作指南</title>
    <link href="/2025/05/30/hexo_note/"/>
    <url>/2025/05/30/hexo_note/</url>
    
    <content type="html"><![CDATA[<h2 id="目录"><a href="#目录" class="headerlink" title="目录"></a>目录</h2><ul><li><a href="#%E7%9B%AE%E5%BD%95">目录</a></li><li><a href="#1-%E5%8F%82%E8%80%83%E6%95%99%E7%A8%8B">1. 参考教程</a><ul><li><a href="#11-nodejs%E5%AE%89%E8%A3%85%E6%95%99%E7%A8%8B">1.1 nodejs安装教程</a></li><li><a href="#12-windows%E4%B8%8Bhexogitee%E6%90%AD%E5%BB%BA%E5%8D%9A%E5%AE%A2%E6%95%99%E7%A8%8B">1.2 Windows下hexo+gitee搭建博客教程</a></li><li><a href="#13-windows%E4%B8%8Bhexogithub%E6%90%AD%E5%BB%BA%E5%8D%9A%E5%AE%A2%E6%95%99%E7%A8%8B">1.3 Windows下hexo+github搭建博客教程</a></li></ul></li><li><a href="#2-%E4%B8%AA%E4%BA%BA%E7%AC%94%E8%AE%B0">2. 个人笔记</a><ul><li><a href="#21-%E4%B8%80%E8%88%AC%E5%B7%A5%E4%BD%9C%E5%AE%8C%E6%95%B4%E6%B5%81%E7%A8%8B">2.1 一般工作完整流程</a></li><li><a href="#22-%E8%A1%A5%E5%85%85%E8%AF%B4%E6%98%8E">2.2 补充说明</a></li></ul></li><li><a href="#3-_configyml%E6%96%87%E4%BB%B6%E4%BB%8B%E7%BB%8D">3. _config.yml文件介绍</a><ul><li><a href="#1-%E7%AB%99%E7%82%B9%E4%BF%A1%E6%81%AFsite">1. 站点信息（Site）</a></li><li><a href="#2-%E7%BD%91%E5%9D%80%E8%AE%BE%E7%BD%AEurl">2. 网址设置（URL）</a></li><li><a href="#3-%E7%9B%AE%E5%BD%95%E8%AE%BE%E7%BD%AEdirectory">3. 目录设置（Directory）</a></li><li><a href="#4-%E5%86%99%E4%BD%9C%E7%9B%B8%E5%85%B3writing">4. 写作相关（Writing）</a></li><li><a href="#5-%E9%A6%96%E9%A1%B5%E8%AE%BE%E7%BD%AEhome-page-setting">5. 首页设置（Home page setting）</a></li><li><a href="#6-%E5%88%86%E7%B1%BB%E4%B8%8E%E6%A0%87%E7%AD%BEcategory--tag">6. 分类与标签（Category &amp; Tag）</a></li><li><a href="#7-%E5%85%83%E6%95%B0%E6%8D%AEmetadata-elements">7. 元数据（Metadata elements）</a></li><li><a href="#8-%E6%97%B6%E9%97%B4%E6%A0%BC%E5%BC%8Fdate--time-format">8. 时间格式（Date &#x2F; Time format）</a></li><li><a href="#9-%E5%88%86%E9%A1%B5pagination">9. 分页（Pagination）</a></li><li><a href="#10-%E5%8C%85%E5%90%AB%E6%8E%92%E9%99%A4%E6%96%87%E4%BB%B6include--exclude-files">10. 包含&#x2F;排除文件（Include &#x2F; Exclude file(s)）</a></li><li><a href="#11-%E6%89%A9%E5%B1%95extensions">11. 扩展（Extensions）</a></li><li><a href="#12-%E9%83%A8%E7%BD%B2deployment">12. 部署（Deployment）</a></li></ul></li><li><a href="#4-%E4%B8%BB%E9%A2%98%E7%BE%8E%E5%8C%96">4. 主题美化</a><ul><li><a href="#41-%E6%9B%B4%E6%8D%A2%E6%96%87%E5%AD%97">4.1 更换文字</a></li><li><a href="#41-%E6%9B%B4%E6%8D%A2%E5%9B%BE%E7%89%87">4.1 更换图片</a></li></ul></li></ul><h2 id="1-参考教程"><a href="#1-参考教程" class="headerlink" title="1. 参考教程"></a>1. 参考教程</h2><h3 id="1-1-nodejs安装教程"><a href="#1-1-nodejs安装教程" class="headerlink" title="1.1 nodejs安装教程"></a>1.1 nodejs安装教程</h3><p><a href="https://blog.csdn.net/WHF__/article/details/129362462">2024最新版Node.js下载安装及环境配置教程【保姆级】</a></p><h3 id="1-2-Windows下hexo-gitee搭建博客教程"><a href="#1-2-Windows下hexo-gitee搭建博客教程" class="headerlink" title="1.2 Windows下hexo+gitee搭建博客教程"></a>1.2 Windows下hexo+gitee搭建博客教程</h3><p><a href="https://zhuanlan.zhihu.com/p/363620650">在Windows系统下使用 Hexo+gitee 搭建博客</a></p><h3 id="1-3-Windows下hexo-github搭建博客教程"><a href="#1-3-Windows下hexo-github搭建博客教程" class="headerlink" title="1.3 Windows下hexo+github搭建博客教程"></a>1.3 Windows下hexo+github搭建博客教程</h3><p><a href="https://www.cnblogs.com/junlin623/p/17410016.html">Windows下hexo个人博客详细搭建教程</a></p><h2 id="2-个人笔记"><a href="#2-个人笔记" class="headerlink" title="2. 个人笔记"></a>2. 个人笔记</h2><h3 id="2-1-一般工作完整流程"><a href="#2-1-一般工作完整流程" class="headerlink" title="2.1 一般工作完整流程"></a>2.1 一般工作完整流程</h3><p>（新增或更新 Hexo 博客并部署上线）</p><ol><li><p><strong>新建或编辑文章</strong><br>在 <code>source/_posts/</code> 目录下新建 Markdown 文件，或修改已有文章。</p></li><li><p><strong>清理旧文件</strong></p><figure class="highlight shell"><table><tr><td class="gutter"><pre><span class="line">1</span><br></pre></td><td class="code"><pre><code class="hljs shell">hexo clean<br></code></pre></td></tr></table></figure><p>清除缓存和旧的生成文件，避免异常。</p></li><li><p><strong>生成静态页面</strong></p><figure class="highlight shell"><table><tr><td class="gutter"><pre><span class="line">1</span><br></pre></td><td class="code"><pre><code class="hljs shell">hexo g<br></code></pre></td></tr></table></figure><p>根据 Markdown 文章生成静态网页文件。</p></li><li><p><strong>本地预览（可选）</strong></p><figure class="highlight shell"><table><tr><td class="gutter"><pre><span class="line">1</span><br></pre></td><td class="code"><pre><code class="hljs shell">hexo s<br></code></pre></td></tr></table></figure><p>启动本地服务器，访问<code>http://localhost:4000</code>检查效果。</p></li><li><p><strong>部署到线上</strong></p><figure class="highlight shell"><table><tr><td class="gutter"><pre><span class="line">1</span><br></pre></td><td class="code"><pre><code class="hljs shell">hexo d<br></code></pre></td></tr></table></figure><p>将生成的静态文件上传到配置好的服务器（如 GitHub Pages）。</p></li></ol><p><strong>完整流程总结</strong><br>新建&#x2F;编辑文章 → <code>hexo clean</code> → <code>hexo g</code> → <code>hexo s</code>（预览）→ <code>hexo d</code>（部署上线）</p><h3 id="2-2-补充说明"><a href="#2-2-补充说明" class="headerlink" title="2.2 补充说明"></a>2.2 补充说明</h3><ul><li>重新部署博客内容后，如若网页内容未更新，则需要清除浏览器缓存，可以使用以下快捷键：<strong>Ctrl + Shift + R</strong></li><li>标题的日期不能重复，否则会导致文章无法正常显示。</li></ul><h2 id="3-config-yml文件介绍"><a href="#3-config-yml文件介绍" class="headerlink" title="3. _config.yml文件介绍"></a>3. _config.yml文件介绍</h2><h3 id="1-站点信息（Site）"><a href="#1-站点信息（Site）" class="headerlink" title="1. 站点信息（Site）"></a>1. 站点信息（Site）</h3><ul><li><code>title</code>：站点标题。</li><li><code>subtitle</code>：副标题。</li><li><code>description</code>：站点描述。</li><li><code>keywords</code>：关键词。</li><li><code>author</code>：作者名。</li><li><code>language</code>：语言（如 <code>zh-CN</code> 表示中文）。</li><li><code>timezone</code>：时区。</li></ul><h3 id="2-网址设置（URL）"><a href="#2-网址设置（URL）" class="headerlink" title="2. 网址设置（URL）"></a>2. 网址设置（URL）</h3><ul><li><code>url</code>：你博客的主网址（如 GitHub Pages 填你的主页地址）。</li><li><code>permalink</code>：文章永久链接格式。</li><li><code>pretty_urls</code>：美化 URL，去掉 index.html 或 .html。</li></ul><h3 id="3-目录设置（Directory）"><a href="#3-目录设置（Directory）" class="headerlink" title="3. 目录设置（Directory）"></a>3. 目录设置（Directory）</h3><ul><li>各种目录的名称，如 <code>source_dir</code>（源码目录）、<code>public_dir</code>（生成目录）等。</li></ul><h3 id="4-写作相关（Writing）"><a href="#4-写作相关（Writing）" class="headerlink" title="4. 写作相关（Writing）"></a>4. 写作相关（Writing）</h3><ul><li><code>new_post_name</code>：新文章的默认文件名格式。</li><li><code>default_layout</code>：默认布局。</li><li><code>external_link</code>：外链是否新窗口打开等。</li><li><code>syntax_highlighter</code>：代码高亮方式（如 highlight.js）。</li></ul><h3 id="5-首页设置（Home-page-setting）"><a href="#5-首页设置（Home-page-setting）" class="headerlink" title="5. 首页设置（Home page setting）"></a>5. 首页设置（Home page setting）</h3><ul><li><code>index_generator</code>：首页文章分页、排序等设置。</li></ul><h3 id="6-分类与标签（Category-Tag）"><a href="#6-分类与标签（Category-Tag）" class="headerlink" title="6. 分类与标签（Category &amp; Tag）"></a>6. 分类与标签（Category &amp; Tag）</h3><ul><li><code>default_category</code>：默认分类。</li><li><code>category_map</code>、<code>tag_map</code>：分类和标签映射。</li></ul><h3 id="7-元数据（Metadata-elements）"><a href="#7-元数据（Metadata-elements）" class="headerlink" title="7. 元数据（Metadata elements）"></a>7. 元数据（Metadata elements）</h3><ul><li><code>meta_generator</code>：是否生成 meta 标签。</li></ul><h3 id="8-时间格式（Date-Time-format）"><a href="#8-时间格式（Date-Time-format）" class="headerlink" title="8. 时间格式（Date &#x2F; Time format）"></a>8. 时间格式（Date &#x2F; Time format）</h3><ul><li><code>date_format</code>、<code>time_format</code>：日期和时间显示格式。</li><li><code>updated_option</code>：更新时间的依据。</li></ul><h3 id="9-分页（Pagination）"><a href="#9-分页（Pagination）" class="headerlink" title="9. 分页（Pagination）"></a>9. 分页（Pagination）</h3><ul><li><code>per_page</code>：每页显示文章数。</li><li><code>pagination_dir</code>：分页目录名。</li></ul><h3 id="10-包含-排除文件（Include-Exclude-file-s-）"><a href="#10-包含-排除文件（Include-Exclude-file-s-）" class="headerlink" title="10. 包含&#x2F;排除文件（Include &#x2F; Exclude file(s)）"></a>10. 包含&#x2F;排除文件（Include &#x2F; Exclude file(s)）</h3><ul><li><code>include</code>、<code>exclude</code>、<code>ignore</code>：指定哪些文件包含或排除。</li></ul><h3 id="11-扩展（Extensions）"><a href="#11-扩展（Extensions）" class="headerlink" title="11. 扩展（Extensions）"></a>11. 扩展（Extensions）</h3><ul><li><code>theme</code>：主题名称。</li><li>插件、主题相关配置。</li></ul><h3 id="12-部署（Deployment）"><a href="#12-部署（Deployment）" class="headerlink" title="12. 部署（Deployment）"></a>12. 部署（Deployment）</h3><ul><li><code>deploy</code>：部署方式，这里用 git，将生成的静态文件推送到 GitHub Pages。</li></ul><h2 id="4-主题美化"><a href="#4-主题美化" class="headerlink" title="4. 主题美化"></a>4. 主题美化</h2><h3 id="4-1-更换文字"><a href="#4-1-更换文字" class="headerlink" title="4.1 更换文字"></a>4.1 更换文字</h3><figure class="highlight yml"><table><tr><td class="gutter"><pre><span class="line">1</span><br><span class="line">2</span><br><span class="line">3</span><br><span class="line">4</span><br><span class="line">5</span><br><span class="line">6</span><br></pre></td><td class="code"><pre><code class="hljs yml"><span class="hljs-attr">slogan:</span><br>  <span class="hljs-attr">enable:</span> <span class="hljs-literal">true</span><br><br>  <span class="hljs-comment"># 为空则按 hexo config.subtitle 显示</span><br>  <span class="hljs-comment"># If empty, text based on `subtitle` in hexo config</span><br>  <span class="hljs-attr">text:</span> <span class="hljs-string">&quot;An elegant Material-Design theme for Hexo&quot;</span> <span class="hljs-comment"># 504行</span><br></code></pre></td></tr></table></figure><h3 id="4-1-更换图片"><a href="#4-1-更换图片" class="headerlink" title="4.1 更换图片"></a>4.1 更换图片</h3><p>将图片复制到该路径 <code>\blog\themes\fluid\source\img\default.png</code></p>]]></content>
    
    
    
    <tags>
      
      <tag>Hexo</tag>
      
      <tag>博客</tag>
      
      <tag>部署</tag>
      
      <tag>教程</tag>
      
      <tag>GitHub</tag>
      
      <tag>Gitee</tag>
      
    </tags>
    
  </entry>
  
  
  
  
</search>
